{
  "prayer_times": [
    {
      "date": "2025-04-29",
      "day": "الثلاثاء",
      "fajr": "05:02",
      "shorouk": "06:37",
      "duhr": "13:30",
      "asr": "17:07",
      "maghrib": "20:14",
      "isha": "21:36"
    },
    {
      "date": "2025-04-30",
      "day": "الأربعاء",
      "fajr": "05:01",
      "shorouk": "06:36",
      "duhr": "13:30",
      "asr": "17:07",
      "maghrib": "20:15",
      "isha": "21:37"
    },
    {
      "date": "2025-05-01",
      "day": "الخميس",
      "fajr": "05:00",
      "shorouk": "06:35",
      "duhr": "13:29",
      "asr": "17:07",
      "maghrib": "20:15",
      "isha": "21:38"
    },
    {
      "date": "2025-05-02",
      "day": "الجمعة",
      "fajr": "04:58",
      "shorouk": "06:34",
      "duhr": "13:29",
      "asr": "17:07",
      "maghrib": "20:16",
      "isha": "21:39"
    },
    {
      "date": "2025-05-03",
      "day": "السبت",
      "fajr": "04:57",
      "shorouk": "06:33",
      "duhr": "13:29",
      "asr": "17:07",
      "maghrib": "20:17",
      "isha": "21:40"
    },
    {
      "date": "2025-05-04",
      "day": "الأحد",
      "fajr": "04:55",
      "shorouk": "06:32",
      "duhr": "13:29",
      "asr": "17:08",
      "maghrib": "20:18",
      "isha": "21:41"
    },
    {
      "date": "2025-05-05",
      "day": "الإثنين",
      "fajr": "04:54",
      "shorouk": "06:31",
      "duhr": "13:29",
      "asr": "17:08",
      "maghrib": "20:18",
      "isha": "21:42"
    },
    {
      "date": "2025-05-06",
      "day": "الثلاثاء",
      "fajr": "04:53",
      "shorouk": "06:30",
      "duhr": "13:29",
      "asr": "17:08",
      "maghrib": "20:19",
      "isha": "21:44"
    },
    {
      "date": "2025-05-07",
      "day": "الأربعاء",
      "fajr": "04:52",
      "shorouk": "06:29",
      "duhr": "13:29",
      "asr": "17:08",
      "maghrib": "20:20",
      "isha": "21:45"
    },
    {
      "date": "2025-05-08",
      "day": "الخميس",
      "fajr": "04:50",
      "shorouk": "06:28",
      "duhr": "13:29",
      "asr": "17:08",
      "maghrib": "20:21",
      "isha": "21:46"
    },
    {
      "date": "2025-05-09",
      "day": "الجمعة",
      "fajr": "04:49",
      "shorouk": "06:28",
      "duhr": "13:29",
      "asr": "17:08",
      "maghrib": "20:22",
      "isha": "21:47"
    },
    {
      "date": "2025-05-10",
      "day": "السبت",
      "fajr": "04:48",
      "shorouk": "06:27",
      "duhr": "13:29",
      "asr": "17:08",
      "maghrib": "20:22",
      "isha": "21:48"
    },
    {
      "date": "2025-05-11",
      "day": "الأحد",
      "fajr": "04:47",
      "shorouk": "06:26",
      "duhr": "13:29",
      "asr": "17:08",
      "maghrib": "20:23",
      "isha": "21:49"
    },
    {
      "date": "2025-05-12",
      "day": "الإثنين",
      "fajr": "04:46",
      "shorouk": "06:25",
      "duhr": "13:29",
      "asr": "17:08",
      "maghrib": "20:24",
      "isha": "21:50"
    },
    {
      "date": "2025-05-13",
      "day": "الثلاثاء",
      "fajr": "04:44",
      "shorouk": "06:24",
      "duhr": "13:29",
      "asr": "17:08",
      "maghrib": "20:25",
      "isha": "21:51"
    },
    {
      "date": "2025-05-14",
      "day": "الأربعاء",
      "fajr": "04:43",
      "shorouk": "06:24",
      "duhr": "13:29",
      "asr": "17:08",
      "maghrib": "20:25",
      "isha": "21:52"
    },
    {
      "date": "2025-05-15",
      "day": "الخميس",
      "fajr": "04:42",
      "shorouk": "06:23",
      "duhr": "13:29",
      "asr": "17:08",
      "maghrib": "20:26",
      "isha": "21:53"
    },
    {
      "date": "2025-05-16",
      "day": "الجمعة",
      "fajr": "04:41",
      "shorouk": "06:22",
      "duhr": "13:29",
      "asr": "17:08",
      "maghrib": "20:27",
      "isha": "21:54"
    },
    {
      "date": "2025-05-17",
      "day": "السبت",
      "fajr": "04:40",
      "shorouk": "06:21",
      "duhr": "13:29",
      "asr": "17:09",
      "maghrib": "20:28",
      "isha": "21:55"
    },
    {
      "date": "2025-05-18",
      "day": "الأحد",
      "fajr": "04:39",
      "shorouk": "06:21",
      "duhr": "13:29",
      "asr": "17:09",
      "maghrib": "20:28",
      "isha": "21:56"
    },
    {
      "date": "2025-05-19",
      "day": "الإثنين",
      "fajr": "04:38",
      "shorouk": "06:20",
      "duhr": "13:29",
      "asr": "17:09",
      "maghrib": "20:29",
      "isha": "21:57"
    },
    {
      "date": "2025-05-20",
      "day": "الثلاثاء",
      "fajr": "04:37",
      "shorouk": "06:19",
      "duhr": "13:29",
      "asr": "17:09",
      "maghrib": "20:30",
      "isha": "21:58"
    },
    {
      "date": "2025-05-21",
      "day": "الأربعاء",
      "fajr": "04:36",
      "shorouk": "06:19",
      "duhr": "13:29",
      "asr": "17:09",
      "maghrib": "20:31",
      "isha": "21:59"
    },
    {
      "date": "2025-05-22",
      "day": "الخميس",
      "fajr": "04:35",
      "shorouk": "06:18",
      "duhr": "13:29",
      "asr": "17:09",
      "maghrib": "20:31",
      "isha": "22:00"
    },
    {
      "date": "2025-05-23",
      "day": "الجمعة",
      "fajr": "04:34",
      "shorouk": "06:18",
      "duhr": "13:29",
      "asr": "17:09",
      "maghrib": "20:32",
      "isha": "22:01"
    },
    {
      "date": "2025-05-24",
      "day": "السبت",
      "fajr": "04:33",
      "shorouk": "06:17",
      "duhr": "13:29",
      "asr": "17:09",
      "maghrib": "20:33",
      "isha": "22:02"
    },
    {
      "date": "2025-05-25",
      "day": "الأحد",
      "fajr": "04:33",
      "shorouk": "06:17",
      "duhr": "13:29",
      "asr": "17:10",
      "maghrib": "20:33",
      "isha": "22:03"
    },
    {
      "date": "2025-05-26",
      "day": "الإثنين",
      "fajr": "04:32",
      "shorouk": "06:16",
      "duhr": "13:29",
      "asr": "17:10",
      "maghrib": "20:34",
      "isha": "22:04"
    },
    {
      "date": "2025-05-27",
      "day": "الثلاثاء",
      "fajr": "04:31",
      "shorouk": "06:16",
      "duhr": "13:30",
      "asr": "17:10",
      "maghrib": "20:35",
      "isha": "22:05"
    },
    {
      "date": "2025-05-28",
      "day": "الأربعاء",
      "fajr": "04:30",
      "shorouk": "06:15",
      "duhr": "13:30",
      "asr": "17:10",
      "maghrib": "20:35",
      "isha": "22:06"
    }
  ]
}